cogneato.py
cogneato-0.2.dist-info/LICENSE
cogneato-0.2.dist-info/WHEEL
cogneato-0.2.dist-info/METADATA
cogneato-0.2.dist-info/RECORD
