Metadata-Version: 2.1
Name: cogneato
Version: 0.2
Summary: API for Cogneato, a tool for experimental optimization.
Author-email: Cogneato <info@cogneato.xyz>
Classifier: License :: OSI Approved :: MIT License
Project-URL: Home, https://cogneato.xyz
